LightPipes/__init__.py
LightPipes/_version.py
LightPipes/config.py
LightPipes/core.py
LightPipes/field.py
LightPipes/lenses.py
LightPipes/misc.py
LightPipes/plotutils.py
LightPipes/propagators.py
LightPipes/sources.py
LightPipes/subs.py
LightPipes/tictoc.py
LightPipes/units.py
LightPipes/unwrap.py
LightPipes/userfunc.py
LightPipes/wavefront.py
LightPipes/zernike.py
LightPipes/zernikemath.py
LightPipes-2.1.5.dist-info/LICENSE.txt
LightPipes-2.1.5.dist-info/METADATA
LightPipes-2.1.5.dist-info/WHEEL
LightPipes-2.1.5.dist-info/top_level.txt
LightPipes-2.1.5.dist-info/RECORD
