Metadata-Version: 2.1
Name: LightPipes
Version: 2.1.5
Summary: LightPipes for Python optical toolbox
Home-page: https://github.com/opticspy/lightpipes
Download-URL: https://github.com/opticspy/lightpipes/releases
Author: Fred van Goor
Author-email: Fred511949@gmail.com
License: BSD-3-Clause
Classifier: Development Status :: 3 - Alpha
Classifier: Programming Language :: Python :: 3
Classifier: License :: OSI Approved :: MIT License
Classifier: Operating System :: OS Independent
License-File: LICENSE.txt
Requires-Dist: numpy
Requires-Dist: scipy
Requires-Dist: matplotlib
Provides-Extra: pyfftw
Requires-Dist: pyfftw ; extra == 'pyfftw'
